<?xml version="1.0" encoding="UTF-8" standalone="no"?><Atividade><atividade ano="2019" campusId="1" descricao="Férias" id="1" legendaId="3" periodoAte="31/01/2019" periodoDe="02/01/2019"/><atividade ano="2019" campusId="1" descricao="ano novo" id="2" legendaId="1" periodoAte="01/01/2019" periodoDe="01/01/2019"/><atividade ano="2019" campusId="1" descricao="Confraternização Universal" id="3" legendaId="1" periodoAte="01/01/2019" periodoDe="01/01/2019"/><atividade ano="2019" campusId="1" descricao="Férias docente" id="4" legendaId="3" periodoAte="31/01/2019" periodoDe="02/01/2019"/><atividade ano="2019" campusId="1" descricao="Planejamento de ensino" id="5" legendaId="8" periodoAte="07/02/2019" periodoDe="01/02/2019"/><atividade ano="2019" campusId="1" descricao="Entrega dos planos de ensino" id="6" legendaId="11" periodoAte="08/02/2019" periodoDe="08/02/2019"/><atividade ano="2019" campusId="1" descricao="Início letivo 2019/1" id="7" legendaId="9" periodoAte="11/02/2019" periodoDe="11/02/2019"/><atividade ano="2019" campusId="1" descricao="Recesso/Carnaval" id="8" legendaId="4" periodoAte="06/03/2019" periodoDe="04/03/2019"/><atividade ano="2019" campusId="1" descricao="Sábado letivo (ref. quarta-feira)" id="9" legendaId="7" periodoAte="16/03/2019" periodoDe="16/03/2019"/><atividade ano="2019" campusId="1" descricao="Lançamento da primeira nota parcial" id="10" legendaId="6" periodoAte="18/04/2019" periodoDe="18/04/2019"/><atividade ano="2019" campusId="1" descricao="Paixão de Cristo" id="11" legendaId="1" periodoAte="19/04/2019" periodoDe="19/04/2019"/><atividade ano="2019" campusId="1" descricao="Tiradentes" id="12" legendaId="1" periodoAte="21/04/2019" periodoDe="21/04/2019"/><atividade ano="2019" campusId="1" descricao="Dia Mundial do Trabalho" id="13" legendaId="1" periodoAte="01/05/2019" periodoDe="01/05/2019"/><atividade ano="2019" campusId="1" descricao="Padroeira de Naviraí" id="14" legendaId="2" periodoAte="13/06/2019" periodoDe="13/06/2019"/><atividade ano="2019" campusId="1" descricao="Sábado letivo (ref. segunda-feira)" id="15" legendaId="7" periodoAte="25/05/2019" periodoDe="25/05/2019"/><atividade ano="2019" campusId="1" descricao="Sábado letivo (ref. sexta-feira)" id="16" legendaId="7" periodoAte="01/06/2019" periodoDe="01/06/2019"/><atividade ano="2019" campusId="1" descricao="Semana do Meio Ambiente" id="17" legendaId="10" periodoAte="07/06/2019" periodoDe="03/06/2019"/><atividade ano="2019" campusId="1" descricao="Corpus Christi" id="18" legendaId="1" periodoAte="20/06/2019" periodoDe="20/06/2019"/><atividade ano="2019" campusId="1" descricao="Recesso" id="19" legendaId="4" periodoAte="21/06/2019" periodoDe="21/06/2019"/><atividade ano="2019" campusId="1" descricao="Entrega de diários/notas" id="20" legendaId="5" periodoAte="05/07/2019" periodoDe="05/07/2019"/><atividade ano="2019" campusId="1" descricao="Término das aulas" id="21" legendaId="9" periodoAte="05/07/2019" periodoDe="05/07/2019"/><atividade ano="2019" campusId="1" descricao="Férias docentes" id="22" legendaId="3" periodoAte="22/07/2019" periodoDe="08/07/2019"/><atividade ano="2019" campusId="1" descricao="Entrega de relatórios" id="23" legendaId="11" periodoAte="24/07/2019" periodoDe="23/07/2019"/><atividade ano="2019" campusId="1" descricao="Planejamento de ensino" id="24" legendaId="8" periodoAte="26/07/2019" periodoDe="25/07/2019"/><atividade ano="2019" campusId="1" descricao="Entrega dos planos de ensino" id="25" legendaId="11" periodoAte="29/07/2019" periodoDe="29/07/2019"/><atividade ano="2019" campusId="1" descricao="Início letivo 2019/2" id="26" legendaId="9" periodoAte="29/07/2019" periodoDe="29/07/2019"/><atividade ano="2019" campusId="1" descricao="Independência do Brasil" id="27" legendaId="1" periodoAte="07/09/2019" periodoDe="07/09/2019"/><atividade ano="2019" campusId="1" descricao="Semana de Ciência e Tecnologia" id="28" legendaId="10" periodoAte="04/10/2019" periodoDe="30/09/2019"/><atividade ano="2019" campusId="1" descricao="Lançamento da primeira nota parcial no sistema" id="29" legendaId="6" periodoAte="07/10/2019" periodoDe="07/10/2019"/><atividade ano="2019" campusId="1" descricao="Ajuste de horário (ref. sexta-feira)" id="30" legendaId="10" periodoAte="08/10/2019" periodoDe="08/10/2019"/><atividade ano="2019" campusId="1" descricao="Divisão do estado" id="31" legendaId="1" periodoAte="11/10/2019" periodoDe="11/10/2019"/><atividade ano="2019" campusId="1" descricao="Padroeira do Brasil" id="32" legendaId="1" periodoAte="12/10/2019" periodoDe="12/10/2019"/><atividade ano="2019" campusId="1" descricao="Dia do Servidor Público" id="33" legendaId="1" periodoAte="28/10/2019" periodoDe="28/10/2019"/><atividade ano="2019" campusId="1" descricao="Finados" id="34" legendaId="1" periodoAte="02/11/2019" periodoDe="02/11/2019"/><atividade ano="2019" campusId="1" descricao="Aniversário de Naviraí" id="35" legendaId="2" periodoAte="11/11/2019" periodoDe="11/11/2019"/><atividade ano="2019" campusId="1" descricao="Proclamação da República" id="36" legendaId="1" periodoAte="15/11/2019" periodoDe="15/11/2019"/><atividade ano="2019" campusId="1" descricao="Ajuste de horário (ref. sexa-feira)" id="37" legendaId="10" periodoAte="20/11/2019" periodoDe="20/11/2019"/><atividade ano="2019" campusId="1" descricao="Sábado letivo (ref. segunda-feira)" id="38" legendaId="7" periodoAte="30/11/2019" periodoDe="30/11/2019"/><atividade ano="2019" campusId="1" descricao="Término das aulas" id="39" legendaId="9" periodoAte="18/12/2019" periodoDe="18/12/2019"/><atividade ano="2019" campusId="1" descricao="Entrega de diários/notas" id="40" legendaId="5" periodoAte="20/12/2019" periodoDe="19/12/2019"/><atividade ano="2019" campusId="1" descricao="Recesso" id="41" legendaId="4" periodoAte="31/12/2019" periodoDe="23/12/2019"/><atividade ano="2019" campusId="1" descricao="Natal" id="42" legendaId="1" periodoAte="25/12/2019" periodoDe="25/12/2019"/></Atividade>